pion/__init__.py
pion/common/__init__.py
pion/common/interfaces.py
pion/simple_scanners/__init__.py
pion/simple_scanners/bls/__init__.py
pion/simple_scanners/bls/scanner.py
pion/simple_scanners/fred/__init__.py
pion/simple_scanners/fred/scanner.py
pion-0.2.2.dist-info/LICENSE
pion-0.2.2.dist-info/METADATA
pion-0.2.2.dist-info/WHEEL
pion-0.2.2.dist-info/top_level.txt
pion-0.2.2.dist-info/RECORD
