Metadata-Version: 2.1
Name: pion
Version: 0.2.2
Summary: A Python project for time series data and databases.
Author-email: Emin Martinian <emin@aocks.com>
License: MIT License
Project-URL: Homepage, https://github.com/aocks/pion-ts
Project-URL: Documentation, https://github.com/aocks/pion-ts
Project-URL: Repository, https://github.com/aocks/pion-ts.git
Project-URL: Issues, https://github.com/aocks/pion-ts/issues
License-File: LICENSE
Requires-Dist: requests
Requires-Dist: numpy
Requires-Dist: pandas
Provides-Extra: dev
Requires-Dist: pytest; extra == "dev"
Requires-Dist: pylint; extra == "dev"
